.gitignore
CHANGES.txt
MANIFEST.in
README.rst
personalize.py
setup.py
validation-files.yaml
validation-options.yaml
imageportlet/__init__.py
imageportlet/cache.zcml
imageportlet/configure.zcml
imageportlet/helpers.py
imageportlet/interfaces.py
imageportlet/plone3.py
imageportlet/portlets.py
imageportlet/views.py
imageportlet/z3cformhelper.py
imageportlet.egg-info/PKG-INFO
imageportlet.egg-info/SOURCES.txt
imageportlet.egg-info/dependency_links.txt
imageportlet.egg-info/entry_points.txt
imageportlet.egg-info/not-zip-safe
imageportlet.egg-info/requires.txt
imageportlet.egg-info/top_level.txt
imageportlet/locales/README.txt
imageportlet/profiles/default/browserlayer.xml
imageportlet/profiles/default/cssregistry.xml
imageportlet/profiles/default/jsregistry.xml
imageportlet/profiles/default/portlets.xml
imageportlet/static/jquery.cycle.lite.js
imageportlet/static/main.css
imageportlet/static/main.js
imageportlet/templates/imageportlet.pt