Metadata-Version: 1.1
Name: imageportlet
Version: 1.1
Summary: imageportlet add-on provides a portlet for Plone CMS for easily add images, banners and carousels around the content on your site
Home-page: http://opensourcehacker.com
Author: Mikko Ohtamaa
Author-email: mikko@opensourcehacker.com
License: GPL2
Platform: UNKNOWN
Classifier: Framework :: Plone
Classifier: Programming Language :: Python
